Metadata-Version: 2.4
Name: cp2025
Version: 1.0.3
Summary: Depersonalization algorithms for course project 2025
Author: Shompolov Maxim
Requires-Python: >=3.10
Requires-Dist: ECPy==1.2.5
Requires-Dist: importlib_metadata==7.0.1
Requires-Dist: numpy==1.26.4
Requires-Dist: pandas==2.2.2
Requires-Dist: scikit_learn==1.4.2
Requires-Dist: scipy==1.13.1
